proton_db/__init__.py
proton_db-0.1.5.dist-info/WHEEL
proton_db-0.1.5.dist-info/METADATA
proton_db-0.1.5.dist-info/RECORD
