Metadata-Version: 2.1
Name: proton-db
Version: 0.1.5
Summary: A simple wrapper for the unofficial Proton-DB API.
Author: BiFr0st
Requires-Python: >=3.10,<4.0
Classifier: Programming Language :: Python :: 3
Classifier: Programming Language :: Python :: 3.10
